{
	"id": "72ba950c-52cd-4436-8e5b-ff452c09a70d",
	"name": "Sept23-Movies",
	"values": [
		{
			"key": "PORT",
			"value": "localhost:4005",
			"type": "default",
			"enabled": true
		},
		{
			"key": "MOVIEID",
			"value": "6580d8944f8064b2a2aa9df3",
			"type": "default",
			"enabled": true
		},
		{
			"key": "JWT",
			"value": "",
			"type": "default",
			"enabled": true
		}
	],
	"_postman_variable_scope": "environment",
	"_postman_exported_at": "2023-12-19T01:43:44.587Z",
	"_postman_exported_using": "Postman/10.21.3"
}